MANIFEST.in
README.rst
pyqode_uic.py
setup.py
pyqode_uic.egg-info/PKG-INFO
pyqode_uic.egg-info/SOURCES.txt
pyqode_uic.egg-info/dependency_links.txt
pyqode_uic.egg-info/entry_points.txt
pyqode_uic.egg-info/top_level.txt