Metadata-Version: 1.0
Name: pyqode-uic
Version: 0.1
Summary: pyQode Qt ui compiler
Home-page: https://github.com/pyQode/pyqode-pyuic
Author: Colin Duquesnoy
Author-email: colin.duquesnoy
License: MIT
Platform: UNKNOWN
